osu_cleaner_cli.py
osu_cleaner_cli-0.0.4.dist-info/LICENSE
osu_cleaner_cli-0.0.4.dist-info/METADATA
osu_cleaner_cli-0.0.4.dist-info/WHEEL
osu_cleaner_cli-0.0.4.dist-info/entry_points.txt
osu_cleaner_cli-0.0.4.dist-info/top_level.txt
osu_cleaner_cli-0.0.4.dist-info/RECORD
