Metadata-Version: 2.1
Name: osu-cleaner-cli
Version: 0.0.4
Summary: Remove unwanted files from osu! Songs directory.
Home-page: https://github.com/Layerex/osu-cleaner-cli
Author: Layerex
Author-email: layerex@dismail.de
Classifier: Development Status :: 6 - Mature
Classifier: Programming Language :: Python :: 3
Classifier: License :: OSI Approved :: GNU General Public License v3 (GPLv3)
Classifier: Operating System :: OS Independent
Classifier: Topic :: Utilities
License-File: LICENSE
